package_346234293/__init__.py
package_346234293/example.py
package_346234293-1.0.1.dist-info/METADATA
package_346234293-1.0.1.dist-info/WHEEL
package_346234293-1.0.1.dist-info/top_level.txt
package_346234293-1.0.1.dist-info/RECORD
